epidemik/EpiModel.py
epidemik/MetaEpiModel.py
epidemik/NetworkEpiModel.py
epidemik/__init__.py
epidemik/utils.py
epidemik-0.1.3.3.dist-info/LICENSE
epidemik-0.1.3.3.dist-info/METADATA
epidemik-0.1.3.3.dist-info/WHEEL
epidemik-0.1.3.3.dist-info/RECORD
