Metadata-Version: 2.3
Name: epidemik
Version: 0.1.3.3
Summary: A package to simulate compartmental epidemic models
Author: Bruno Gonçalves
Author-email: bgoncalves@data4sci.com
Requires-Python: >=3.9
Classifier: Programming Language :: Python :: 3
Classifier: License :: OSI Approved :: MIT License
Classifier: Operating System :: OS Independent
Requires-Dist: matplotlib (>=3.3)
Requires-Dist: networkx (>=3)
Requires-Dist: numpy (>=1.20)
Requires-Dist: pandas (>=2.0)
Requires-Dist: pyyaml (>=6.0.2,<7.0.0)
Requires-Dist: scikit-learn (>=1.6.1,<2.0.0)
Requires-Dist: scipy (>=1.7)
Requires-Dist: seaborn (>=0.13.2,<0.14.0)
Requires-Dist: tqdm (>=4)
Requires-Dist: typing-extensions (>=4.13.0,<5.0.0)
Project-URL: Documentation, https://epidemik.readthedocs.io/
Project-URL: Homepage, https://github.com/DataForScience/epidemik
Project-URL: Issues, https://github.com/DataForScience/epidemik/issues
